istruthy/README.MD
istruthy/__init__.py
istruthy/requirements.txt
istruthy/thirdparty.json
istruthy-0.12.dist-info/LICENSE.rst
istruthy-0.12.dist-info/METADATA
istruthy-0.12.dist-info/WHEEL
istruthy-0.12.dist-info/top_level.txt
istruthy-0.12.dist-info/RECORD
