Metadata-Version: 2.1
Name: istruthy
Version: 0.12
Summary: extends the capability of truthiness evaluation beyond the standard Python truthiness rules to handle pandas DataFrames/Series and NumPy Arrays
Home-page: https://github.com/hansalemaos/istruthy
Author: Johannes Fischer
Author-email: aulasparticularesdealemaosp@gmail.com
License: MIT
Keywords: numpy,pandas,truthy,falsy
Classifier: Development Status :: 4 - Beta
Classifier: Programming Language :: Python :: 3 :: Only
Classifier: Programming Language :: Python :: 3.10
Classifier: Topic :: Software Development :: Libraries :: Python Modules
Classifier: Topic :: Utilities
License-File: LICENSE.rst
